LICENSE.txt
MANIFEST.in
README.md
oemclient.py
requirements.txt
setup.py
oemclient.egg-info/PKG-INFO
oemclient.egg-info/SOURCES.txt
oemclient.egg-info/dependency_links.txt
oemclient.egg-info/entry_points.txt
oemclient.egg-info/requires.txt
oemclient.egg-info/top_level.txt