Metadata-Version: 1.1
Name: oemclient
Version: 0.1.1
Summary: oemclient is a client for the Varolii Xpress API
Home-page: https://github.com/tpe11etier/oemclient
Author: Tony Pelletier
Author-email: tony.pelletier@gmail.com
License: MIT
Platform: UNKNOWN
Classifier: Intended Audience :: Developers
Classifier: Natural Language :: English
Classifier: License :: OSI Approved :: MIT License
Classifier: Programming Language :: Python
Classifier: Programming Language :: Python :: 2
Classifier: Programming Language :: Python :: 2.7
